openmmml/__init__.py
openmmml/mlpotential.py
openmmml/models/__init__.py
openmmml/models/aimnet2potential.py
openmmml/models/anipotential.py
openmmml/models/deepmdpotential.py
openmmml/models/macepotential.py
openmmml/models/nequippotential.py
openmmml-1.4.dist-info/licenses/LICENSE
openmmml-1.4.dist-info/METADATA
openmmml-1.4.dist-info/WHEEL
openmmml-1.4.dist-info/entry_points.txt
openmmml-1.4.dist-info/top_level.txt
openmmml-1.4.dist-info/RECORD
